Metadata-Version: 2.1
Name: pypdfium
Version: 0.0.15
Summary: A simple python wrapper for PDFium
Home-page: https://github.com/YinlinHu/pypdfium
Author: Yinlin Hu
Author-email: huyinlin@gmail.com
License: MIT License
Keywords: Python PDFium
Platform: UNKNOWN
Classifier: License :: OSI Approved :: MIT License
Classifier: Operating System :: POSIX :: Linux
Classifier: Operating System :: MacOS :: MacOS X
Classifier: Operating System :: Microsoft :: Windows
Classifier: Programming Language :: Python :: 3
